jptime/__init__.py
jptime/py.typed
jptime-1.1.0.dist-info/LICENSE
jptime-1.1.0.dist-info/WHEEL
jptime-1.1.0.dist-info/METADATA
jptime-1.1.0.dist-info/RECORD
