Metadata-Version: 2.1
Name: jptime
Version: 1.1.0
Summary: handle japanese time format
Home-page: https://github.com/kitagawa-hr/jptime
Author: kitagawa-hr
Author-email: kitagawahr@gmail.com
Requires-Python: >=3.6,<4.0
Classifier: Development Status :: 4 - Beta
Classifier: Environment :: Web Environment
Classifier: Intended Audience :: Developers
Classifier: Intended Audience :: System Administrators
Classifier: License :: OSI Approved :: MIT License
Classifier: Operating System :: OS Independent
Classifier: Programming Language :: Python
Classifier: Programming Language :: Python :: 3
Classifier: Programming Language :: Python :: 3 :: Only
Classifier: Programming Language :: Python :: 3.10
Classifier: Programming Language :: Python :: 3.6
Classifier: Programming Language :: Python :: 3.7
Classifier: Programming Language :: Python :: 3.8
Classifier: Programming Language :: Python :: 3.9
Classifier: Topic :: Software Development
Classifier: Topic :: Software Development :: Libraries
Classifier: Topic :: Software Development :: Libraries :: Python Modules
Classifier: Typing :: Typed
Requires-Dist: japanese-number-converter (==1.0.1)
Requires-Dist: python-dateutil (>=2.8.1,<3.0.0)
Project-URL: Repository, https://github.com/kitagawa-hr/jptime
